django_simple_affiliate-0.1.dist-info/DESCRIPTION.rst
django_simple_affiliate-0.1.dist-info/METADATA
django_simple_affiliate-0.1.dist-info/RECORD
django_simple_affiliate-0.1.dist-info/WHEEL
django_simple_affiliate-0.1.dist-info/metadata.json
django_simple_affiliate-0.1.dist-info/top_level.txt
simple_affiliate/__init__.py
simple_affiliate/const.py
simple_affiliate/helpers.py
simple_affiliate/middleware.py
