Metadata-Version: 2.0
Name: django-simple-affiliate
Version: 0.1
Summary: Simple Affiliate System for Django
Home-page: https://github.com/czue/django-simple-affiliate
Author: Cory Zue
Author-email: cory@coryzue.com
License: Apache Software License
Keywords: affiliate marketing django middleware tracking
Platform: UNKNOWN
Classifier: Development Status :: 3 - Alpha
Classifier: Intended Audience :: Developers
Classifier: Topic :: Software Development :: Libraries
Classifier: License :: OSI Approved :: Apache Software License
Classifier: Programming Language :: Python :: 2
Classifier: Programming Language :: Python :: 2.7
Classifier: Programming Language :: Python :: 3
Classifier: Programming Language :: Python :: 3.3
Classifier: Programming Language :: Python :: 3.4
Classifier: Programming Language :: Python :: 3.5
Requires-Dist: django
